curriculum_curator/__init__.py
curriculum_curator/cli.py
curriculum_curator/interactive.py
curriculum_curator/config/__init__.py
curriculum_curator/config/models.py
curriculum_curator/config/utils.py
curriculum_curator/content/__init__.py
curriculum_curator/content/transformer.py
curriculum_curator/core/__init__.py
curriculum_curator/core/content.py
curriculum_curator/llm/__init__.py
curriculum_curator/llm/manager.py
curriculum_curator/output/__init__.py
curriculum_curator/persistence/__init__.py
curriculum_curator/persistence/manager.py
curriculum_curator/prompt/__init__.py
curriculum_curator/prompt/editor.py
curriculum_curator/prompt/registry.py
curriculum_curator/remediation/__init__.py
curriculum_curator/remediation/manager.py
curriculum_curator/remediation/remediators/__init__.py
curriculum_curator/remediation/remediators/base.py
curriculum_curator/remediation/remediators/autofix/__init__.py
curriculum_curator/remediation/remediators/autofix/format_corrector.py
curriculum_curator/remediation/remediators/autofix/sentence_splitter.py
curriculum_curator/remediation/remediators/autofix/terminology_enforcer.py
curriculum_curator/remediation/remediators/language/__init__.py
curriculum_curator/remediation/remediators/language/translator.py
curriculum_curator/remediation/remediators/rewrite/__init__.py
curriculum_curator/remediation/remediators/rewrite/rephrasing_prompter.py
curriculum_curator/remediation/remediators/workflow/__init__.py
curriculum_curator/remediation/remediators/workflow/flag_for_review.py
curriculum_curator/tools/__init__.py
curriculum_curator/tools/validate_workflow.py
curriculum_curator/utils/__init__.py
curriculum_curator/utils/exceptions.py
curriculum_curator/utils/logging.py
curriculum_curator/validation/__init__.py
curriculum_curator/validation/manager.py
curriculum_curator/validation/validators/__init__.py
curriculum_curator/validation/validators/base.py
curriculum_curator/validation/validators/accuracy/__init__.py
curriculum_curator-0.2.1.dist-info/licenses/AUTHORS.md
curriculum_curator-0.2.1.dist-info/licenses/LICENSE
curriculum_curator-0.2.1.dist-info/METADATA
curriculum_curator-0.2.1.dist-info/WHEEL
curriculum_curator-0.2.1.dist-info/entry_points.txt
curriculum_curator-0.2.1.dist-info/top_level.txt
curriculum_curator-0.2.1.dist-info/RECORD
