Metadata-Version: 2.4
Name: curriculum-curator
Version: 0.2.1
Summary: An educational content workflow orchestration tool for LLM integration
Author-email: Curriculum Curator Team <example@example.com>
License-Expression: MIT
Project-URL: Homepage, https://github.com/teaching-repositories/curriculum-curator
Project-URL: Bug Tracker, https://github.com/teaching-repositories/curriculum-curator/issues
Project-URL: Documentation, https://github.com/teaching-repositories/curriculum-curator/blob/main/docs
Classifier: Programming Language :: Python :: 3
Classifier: Operating System :: OS Independent
Classifier: Development Status :: 3 - Alpha
Classifier: Intended Audience :: Education
Classifier: Topic :: Education
Classifier: Topic :: Text Processing
Requires-Python: >=3.9
License-File: LICENSE
License-File: AUTHORS.md
Requires-Dist: python-frontmatter>=1.0.0
Requires-Dist: pyyaml>=6.0
Requires-Dist: structlog>=23.1.0
Requires-Dist: litellm>=1.0.0
Requires-Dist: backoff>=2.2.1
Requires-Dist: scikit-learn>=1.2.0
Requires-Dist: typer>=0.9.0
Requires-Dist: rich>=13.3.0
Requires-Dist: markdown>=3.4.0
Requires-Dist: beautifulsoup4>=4.12.0
Requires-Dist: pydantic>=2.5.0
Requires-Dist: sentence-transformers>=2.2.2
Requires-Dist: textstat>=0.7.3
Provides-Extra: dev
Requires-Dist: pytest>=7.3.1; extra == "dev"
Requires-Dist: pytest-asyncio>=0.21.0; extra == "dev"
Requires-Dist: pytest-cov>=4.1.0; extra == "dev"
Requires-Dist: ruff>=0.0.262; extra == "dev"
Requires-Dist: mypy>=1.8.0; extra == "dev"
Requires-Dist: pre-commit>=3.6.0; extra == "dev"
Requires-Dist: isort>=5.13.2; extra == "dev"
Requires-Dist: mkdocs>=1.4.3; extra == "dev"
Requires-Dist: mkdocs-material>=9.1.8; extra == "dev"
Requires-Dist: twine>=6.0.1; extra == "dev"
Requires-Dist: build>=0.10.0; extra == "dev"
Provides-Extra: web
Requires-Dist: fasthtml>=0.2.0; extra == "web"
Dynamic: license-file
